swiftbat/__init__.py
swiftbat/batcatalog.py
swiftbat/catalog
swiftbat/clockinfo.py
swiftbat/generaldir.py
swiftbat/recent_bcttb.fits.gz
swiftbat/sfmisc.py
swiftbat/swinfo.py
swiftbat/swutil.py
swiftbat-0.1.6.dist-info/licenses/LICENSE
swiftbat-0.1.6.dist-info/METADATA
swiftbat-0.1.6.dist-info/WHEEL
swiftbat-0.1.6.dist-info/entry_points.txt
swiftbat-0.1.6.dist-info/top_level.txt
swiftbat-0.1.6.dist-info/RECORD
