Metadata-Version: 2.4
Name: swiftbat
Version: 0.1.6
Summary: Routines for dealing with data from BAT on the Neil Gehrels Swift Observatory
Home-page: https://github.com/lanl/swiftbat_python/
Author: David M. Palmer
Author-email: palmer@lanl.gov
License: BSD-3-Clause
Classifier: Development Status :: 4 - Beta
Classifier: Intended Audience :: Science/Research
Classifier: Programming Language :: Python
Classifier: Programming Language :: Python :: 3
Classifier: Topic :: Scientific/Engineering :: Astronomy
Requires-Python: >=3.9
License-File: LICENSE
Requires-Dist: astropy>=5
Requires-Dist: astroquery>0.4.8
Requires-Dist: numpy
Requires-Dist: python-dateutil
Requires-Dist: skyfield>=1.4
Requires-Dist: swifttools
Dynamic: author
Dynamic: author-email
Dynamic: classifier
Dynamic: description
Dynamic: description-content-type
Dynamic: home-page
Dynamic: license
Dynamic: license-file
Dynamic: requires-dist
Dynamic: requires-python
Dynamic: summary
